pyhcx/__init__.py
pyhcx/api/__init__.py
pyhcx/api/chat_api.py
pyhcx/api/completions_api.py
pyhcx/api/embeddings_api.py
pyhcx/api/fine_tuning_api.py
pyhcx/api/segmentation_api.py
pyhcx/api_client.py
pyhcx/api_response.py
pyhcx/configuration.py
pyhcx/exceptions.py
pyhcx/models/__init__.py
pyhcx/models/chat_completion_message.py
pyhcx/models/chat_completion_result.py
pyhcx/models/completion_ai_filter.py
pyhcx/models/completion_result.py
pyhcx/models/create_chat_completion_request.py
pyhcx/models/create_chat_completion_response.py
pyhcx/models/create_completion_request.py
pyhcx/models/create_completion_response.py
pyhcx/models/create_embedding_request.py
pyhcx/models/create_embedding_response.py
pyhcx/models/create_embedding_result.py
pyhcx/models/create_segmentation_request.py
pyhcx/models/create_segmentation_response.py
pyhcx/models/create_segmentation_result.py
pyhcx/models/delete_training_task200_response.py
pyhcx/models/get_training_task_list_response.py
pyhcx/models/get_training_task_list_result.py
pyhcx/models/get_training_task_list_result_content_inner.py
pyhcx/models/status.py
pyhcx/models/training_task_response.py
pyhcx/models/training_task_result.py
pyhcx/models/training_task_result_status_info.py
pyhcx/py.typed
pyhcx/rest.py
pyhcx-0.9.8.dist-info/METADATA
pyhcx-0.9.8.dist-info/WHEEL
pyhcx-0.9.8.dist-info/RECORD
