Metadata-Version: 2.1
Name: pyhcx
Version: 0.9.8
Summary: HCX API
Home-page: https://gitlab.com/didim365-ai/naver-ai
License: NoLicense
Keywords: OpenAPI,OpenAPI-Generator,HCX API
Author: HCX Support
Author-email: ai@didim365.co.kr
Requires-Python: >=3.7,<4.0
Classifier: License :: Other/Proprietary License
Classifier: Programming Language :: Python :: 3
Classifier: Programming Language :: Python :: 3.7
Classifier: Programming Language :: Python :: 3.8
Classifier: Programming Language :: Python :: 3.9
Classifier: Programming Language :: Python :: 3.10
Classifier: Programming Language :: Python :: 3.11
Classifier: Programming Language :: Python :: 3.12
Requires-Dist: pydantic (>=2)
Requires-Dist: python-dateutil (>=2.8.2)
Requires-Dist: typing-extensions (>=4.7.1)
Requires-Dist: urllib3 (>=1.25.3)
Project-URL: Repository, https://gitlab.com/didim365-ai/naver-ai
